{"id":89373,"communityId":356,"institutionId":3557,"name":"Institute of Transportation Engineers","shortName":"ITE","nameSortKey":"I","websiteKey":"ite","email":"tamuite.president@gmail.com","description":"<p>Welcome to the homepage of the Texas A&amp;M University Student Chapter of the Institute of Transportation Engineers.&nbsp; Our organization is comprised of undergraduate and graduate students from all majors that are interested in transportation engineering.&nbsp; If you have any questions or would like more information about how to join TAMUite, please feel free to contact us.</p>\r\n<p>The purpose of this organization shall be to promote the advancement of transportation engineering. The goals of this organization shall be to foster the closer association of students with the transportation profession and the Institute of Transportation Engineers (ITE), to promote the development of professional spirit, and to identify and address common transportation interests among the student members.</p>","summary":"The purpose of this organization shall be to promote the advancement of transportation engineering. The goals of this organization shall be to foster the closer association of students with the transportation profession and the Institute of Transportat...","status":"Active","comment":null,"showJoin":true,"statusChangeDateTime":null,"startDate":"2013-07-01T00:00:00+00:00","endDate":null,"parentId":85092,"wallId":1302752,"discussionId":1302752,"groupTypeId":null,"organizationTypeId":2756,"cssConfigurationId":null,"deleted":false,"enableGoogleCalendar":false,"modifiedOn":"0001-01-01T00:00:00+00:00","socialMedia":{"ExternalWebsite":"","FlickrUrl":"","GoogleCalendarUrl":"","GooglePlusUrl":"","InstagramUrl":"","LinkedInUrl":"","PinterestUrl":"","TumblrUrl":"","VimeoUrl":"","YoutubeUrl":"","FacebookUrl":"https://www.facebook.com/groups/TAMUite/","TwitterUrl":null,"TwitterUserName":""},"profilePicture":"59c817cc-3685-4ffb-b144-ba00b5ad3a8bb277cfa0-ea1a-42ee-9528-de9ad112a0c7.jpg","organizationType":{"id":2756,"name":"Registered - Recognized Student Organizations","autoApproveRequests":false,"showMembersToPublic":false,"showOfficersToPublic":true,"eventsEnabled":true,"serviceHoursEnabled":true,"financeEnabled":false,"reRegistrationAvailabilty":null,"electionsEnabled":true,"formsEnabled":true,"galleryEnabled":true,"outcomesEnabled":true,"rosterEnabled":true,"shownInPublicDirectory":true,"documentsEnabled":true,"isSystemType":false,"adminOnly":false},"primaryContact":{"id":"3e1c5b69-e1f9-4ce3-8504-4186ecc2d76e","firstName":"Jayson","preferredFirstName":null,"lastName":"Stibbe","primaryEmailAddress":"jstibbe@tamu.edu","profileImageFilePath":null,"institutionId":3557,"privacy":"Unselected"},"isBranch":false,"contactInfo":[{"id":166750,"addressType":0,"city":null,"country":null,"deleted":false,"extension":null,"faxNumber":null,"organizationId":89373,"phoneNumber":null,"state":null,"street1":null,"street2":null,"zip":null}],"legacyKey":null,"parentLegacyKey":null,"legacyPrimaryContactKey":null,"showFacebookWall":false,"showTwitterFeed":false,"submissions":[],"visibility":"Public","isShownInPublicDirectory":true,"isAdminOnly":false,"categories":[]}