{"id":89615,"communityId":356,"institutionId":3557,"name":"Liberal Arts Student Council","shortName":"LASC","nameSortKey":"L","websiteKey":"lasc","email":"liberalartsstudentcouncil@gmail.com","description":"<p>Liberal Arts Student Council (LASC) is an academic and professional organization that links Liberal Arts Students to their college. The Council works to convey concerns and special interests from the undergraduate student body to the faculty, staff, and deans of the college. The Council strives to heighten awareness and assist in the development and refinement of marketable skills for students pursuing a career by hosting a career fair specifically for liberal arts majors. Another pillar of the council is to promote Liberal Arts students in both the university and community through various forms such as advertising, a student based publication, community involvement, and community outreach. <br /> <br /> Members of the Liberal Arts Student Council meet weekly on Wednesday evenings for a general meeting.&nbsp;Members are expected to attend at least three socials and three community service events, as membership is maintained based on attendance and fulfillment of points.&nbsp;</p>","summary":"Liberal Arts Student Council (LASC) is an academic and professional organization that links Liberal Arts Students to their college. The Council works to convey concerns and special interests from the undergraduate student body to the faculty, staff, an...","status":"Active","comment":null,"showJoin":true,"statusChangeDateTime":null,"startDate":"2013-07-01T00:00:00+00:00","endDate":null,"parentId":85092,"wallId":1303320,"discussionId":1303320,"groupTypeId":null,"organizationTypeId":2756,"cssConfigurationId":null,"deleted":false,"enableGoogleCalendar":false,"modifiedOn":"0001-01-01T00:00:00+00:00","socialMedia":{"ExternalWebsite":"http://lasc.tamu.edu","FlickrUrl":"","GoogleCalendarUrl":"","GooglePlusUrl":"","InstagramUrl":"","LinkedInUrl":"","PinterestUrl":"","TumblrUrl":"","VimeoUrl":"","YoutubeUrl":"","FacebookUrl":null,"TwitterUrl":"","TwitterUserName":null},"profilePicture":null,"organizationType":{"id":2756,"name":"Registered - Recognized Student Organizations","autoApproveRequests":false,"showMembersToPublic":false,"showOfficersToPublic":true,"eventsEnabled":true,"serviceHoursEnabled":true,"financeEnabled":false,"reRegistrationAvailabilty":null,"electionsEnabled":true,"formsEnabled":true,"galleryEnabled":true,"outcomesEnabled":true,"rosterEnabled":true,"shownInPublicDirectory":true,"documentsEnabled":true,"isSystemType":false,"adminOnly":false},"primaryContact":{"id":"e1c80905-8c84-46f3-8915-a51600f9d751","firstName":"Mackenzie","preferredFirstName":null,"lastName":"Clayton","primaryEmailAddress":"kenzie2205@tamu.edu","profileImageFilePath":null,"institutionId":3557,"privacy":"Unselected"},"isBranch":false,"contactInfo":[{"id":166984,"addressType":0,"city":null,"country":null,"deleted":false,"extension":null,"faxNumber":null,"organizationId":89615,"phoneNumber":null,"state":null,"street1":null,"street2":null,"zip":null}],"legacyKey":null,"parentLegacyKey":null,"legacyPrimaryContactKey":null,"showFacebookWall":false,"showTwitterFeed":false,"submissions":[],"visibility":"Public","isShownInPublicDirectory":true,"isAdminOnly":false,"categories":[]}