{"id":129335,"communityId":356,"institutionId":3557,"name":"Texas A&M Mock Trial","shortName":"Mock Trial","nameSortKey":"T","websiteKey":"mocktrial","email":null,"description":"<p>Our website has moved! You can now find the Texas A&amp;M Mock Trial team's website at: <a href=\"http://tamumocktrial.weebly.com/\">http://tamumocktrial.weebly.com/</a></p>","summary":"Our website has moved! You can now find the Texas A&M Mock Trial team's website at: http://tamumocktrial.weebly.com/","status":"Active","comment":null,"showJoin":true,"statusChangeDateTime":null,"startDate":"2015-07-13T00:00:00+00:00","endDate":null,"parentId":85092,"wallId":4153986,"discussionId":4153986,"groupTypeId":null,"organizationTypeId":2756,"cssConfigurationId":null,"deleted":false,"enableGoogleCalendar":false,"modifiedOn":"0001-01-01T00:00:00+00:00","socialMedia":{"ExternalWebsite":"http://tamumocktrial.weebly.com","FlickrUrl":"","GoogleCalendarUrl":"","GooglePlusUrl":"","InstagramUrl":"","LinkedInUrl":"","PinterestUrl":"","TumblrUrl":"","VimeoUrl":"","YoutubeUrl":"","FacebookUrl":"https://www.facebook.com/TexasAggieMockTrial/?fref=ts","TwitterUrl":null,"TwitterUserName":""},"profilePicture":"b8c0d2f1-aa95-4293-9ef6-65fbdfd7b9086864178f-3de6-4cd4-a9d4-bd8932524a1b.jpeg","organizationType":{"id":2756,"name":"Registered - Recognized Student Organizations","autoApproveRequests":false,"showMembersToPublic":false,"showOfficersToPublic":true,"eventsEnabled":true,"serviceHoursEnabled":true,"financeEnabled":false,"reRegistrationAvailabilty":null,"electionsEnabled":true,"formsEnabled":true,"galleryEnabled":true,"outcomesEnabled":true,"rosterEnabled":true,"shownInPublicDirectory":true,"documentsEnabled":true,"isSystemType":false,"adminOnly":false},"primaryContact":{"id":"70d1eb84-baa2-4554-b871-a64e00e8fb4f","firstName":"Christina","preferredFirstName":null,"lastName":"Morrison","primaryEmailAddress":"christinamorrison27@tamu.edu","profileImageFilePath":"c3c8bece-7534-4d83-af54-4ed0cc30a05699253939-3f8b-441e-b694-5fd5349adcb3.jpeg","institutionId":3557,"privacy":"Unselected"},"isBranch":false,"contactInfo":[{"id":204123,"addressType":0,"city":null,"country":null,"deleted":false,"extension":null,"faxNumber":null,"organizationId":129335,"phoneNumber":null,"state":null,"street1":null,"street2":null,"zip":null}],"legacyKey":null,"parentLegacyKey":null,"legacyPrimaryContactKey":null,"showFacebookWall":false,"showTwitterFeed":false,"submissions":[],"visibility":"Public","isShownInPublicDirectory":true,"isAdminOnly":false,"categories":[]}