{"id":94169,"communityId":356,"institutionId":3557,"name":"Texas A&M Veteran's Association","shortName":"Veteran Students","nameSortKey":"T","websiteKey":"tamva","email":"tamuveterans@stuact.tamu.edu","description":"<p>To help veterans, active duty, and active duty reservists attending Texas A&amp;M assimilate to the scholastic environment while providing the camaraderie found in the Armed Services.</p>","summary":"To help veterans, active duty, and active duty reservists attending Texas A&M assimilate to the scholastic environment while providing the camaraderie found in the Armed Services.\r\n","status":"Active","comment":null,"showJoin":true,"statusChangeDateTime":null,"startDate":"2013-08-08T00:00:00+00:00","endDate":null,"parentId":85092,"wallId":1355825,"discussionId":1355825,"groupTypeId":null,"organizationTypeId":2756,"cssConfigurationId":null,"deleted":false,"enableGoogleCalendar":false,"modifiedOn":"0001-01-01T00:00:00+00:00","socialMedia":{"ExternalWebsite":"http://aggieveteranlife.com/","FlickrUrl":"","GoogleCalendarUrl":"","GooglePlusUrl":"","InstagramUrl":"","LinkedInUrl":"","PinterestUrl":"","TumblrUrl":"","VimeoUrl":"","YoutubeUrl":"","FacebookUrl":null,"TwitterUrl":"","TwitterUserName":""},"profilePicture":"2041c138-2a2f-45fd-8beb-1aa4c5bbebc1a5a64b4d-e566-47d3-b876-f01cd9b90018.png","organizationType":{"id":2756,"name":"Registered - Recognized Student Organizations","autoApproveRequests":false,"showMembersToPublic":false,"showOfficersToPublic":true,"eventsEnabled":true,"serviceHoursEnabled":true,"financeEnabled":false,"reRegistrationAvailabilty":null,"electionsEnabled":true,"formsEnabled":true,"galleryEnabled":true,"outcomesEnabled":true,"rosterEnabled":true,"shownInPublicDirectory":true,"documentsEnabled":true,"isSystemType":false,"adminOnly":false},"primaryContact":{"id":"86bc10ee-c2bb-48d1-afd6-a7ae00f6e2ab","firstName":"Alyssa","preferredFirstName":null,"lastName":"Knuth","primaryEmailAddress":"alyknuth@tamu.edu","profileImageFilePath":null,"institutionId":3557,"privacy":"Unselected"},"isBranch":false,"contactInfo":[{"id":171367,"addressType":0,"city":null,"country":null,"deleted":false,"extension":null,"faxNumber":null,"organizationId":94169,"phoneNumber":null,"state":null,"street1":null,"street2":null,"zip":null}],"legacyKey":null,"parentLegacyKey":null,"legacyPrimaryContactKey":null,"showFacebookWall":false,"showTwitterFeed":false,"submissions":[],"visibility":"Public","isShownInPublicDirectory":true,"isAdminOnly":false,"categories":[]}