{"id":144487,"communityId":356,"institutionId":3557,"name":"Aggie Golden Arrows","shortName":"AGA","nameSortKey":"A","websiteKey":"arrows","email":null,"description":null,"summary":"The purpose of the Aggie Golden Arrows is to unite diverse women through passion, diversity and service. We aim to give back to Texas A&M University as well as the community.","status":"Active","comment":null,"showJoin":true,"statusChangeDateTime":null,"startDate":"2016-02-10T00:00:00+00:00","endDate":null,"parentId":85092,"wallId":5405498,"discussionId":5405498,"groupTypeId":null,"organizationTypeId":2756,"cssConfigurationId":null,"deleted":false,"enableGoogleCalendar":false,"modifiedOn":"0001-01-01T00:00:00+00:00","socialMedia":{"ExternalWebsite":"","FlickrUrl":"","GoogleCalendarUrl":"","GooglePlusUrl":"","InstagramUrl":"","LinkedInUrl":"","PinterestUrl":"","TumblrUrl":"","VimeoUrl":"","YoutubeUrl":"","FacebookUrl":null,"TwitterUrl":null,"TwitterUserName":null},"profilePicture":null,"organizationType":{"id":2756,"name":"Registered - Recognized Student Organizations","autoApproveRequests":false,"showMembersToPublic":false,"showOfficersToPublic":true,"eventsEnabled":true,"serviceHoursEnabled":true,"financeEnabled":false,"reRegistrationAvailabilty":null,"electionsEnabled":true,"formsEnabled":true,"galleryEnabled":true,"outcomesEnabled":true,"rosterEnabled":true,"shownInPublicDirectory":true,"documentsEnabled":true,"isSystemType":false,"adminOnly":false},"primaryContact":{"id":"a207977e-c831-4479-8030-a487013f84f3","firstName":"Katherine","preferredFirstName":null,"lastName":"Aupperle","primaryEmailAddress":"katie_aupperle1995@tamu.edu","profileImageFilePath":null,"institutionId":3557,"privacy":"Unselected"},"isBranch":false,"contactInfo":[],"legacyKey":null,"parentLegacyKey":null,"legacyPrimaryContactKey":null,"showFacebookWall":false,"showTwitterFeed":false,"submissions":[],"visibility":"Public","isShownInPublicDirectory":true,"isAdminOnly":false,"categories":[]}