{"id":89086,"communityId":356,"institutionId":3557,"name":"Autism Speaks U Texas A&M University","shortName":"","nameSortKey":"A","websiteKey":"autismspeaks","email":"autismspeaks.tamu@gmail.com","description":"<p>The purpose of Autism Speaks U Texas A&amp;M University is to further the mission of the national organization Autism Speaks by engaging the campus and local community through autism awareness, education, and fundraising. In doing so, we strive to positively affect the lives of those with autism spectrum disorders and their families.</p>","summary":null,"status":"Active","comment":null,"showJoin":true,"statusChangeDateTime":null,"startDate":"2013-07-01T00:00:00+00:00","endDate":null,"parentId":85092,"wallId":1302465,"discussionId":1302465,"groupTypeId":null,"organizationTypeId":2756,"cssConfigurationId":null,"deleted":false,"enableGoogleCalendar":false,"modifiedOn":"0001-01-01T00:00:00+00:00","socialMedia":{"ExternalWebsite":"","FlickrUrl":"","GoogleCalendarUrl":"","GooglePlusUrl":"","InstagramUrl":"","LinkedInUrl":"","PinterestUrl":"","TumblrUrl":"","VimeoUrl":"","YoutubeUrl":"","FacebookUrl":"https://www.facebook.com/autismspeaksutamu/","TwitterUrl":null,"TwitterUserName":"ASU_TAMU"},"profilePicture":null,"organizationType":{"id":2756,"name":"Registered - Recognized Student Organizations","autoApproveRequests":false,"showMembersToPublic":false,"showOfficersToPublic":true,"eventsEnabled":true,"serviceHoursEnabled":true,"financeEnabled":false,"reRegistrationAvailabilty":null,"electionsEnabled":true,"formsEnabled":true,"galleryEnabled":true,"outcomesEnabled":true,"rosterEnabled":true,"shownInPublicDirectory":true,"documentsEnabled":true,"isSystemType":false,"adminOnly":false},"primaryContact":{"id":"bcb018c9-0904-4069-b766-a52300ea35c6","firstName":"Emily","preferredFirstName":null,"lastName":"Abalos","primaryEmailAddress":"emilyabalos14@tamu.edu","profileImageFilePath":"22de6f3c-563b-43bb-9fcf-f26099d1d1d8c35874a9-e94f-402f-9cad-264d52ad46b5.jpg","institutionId":3557,"privacy":"Unselected"},"isBranch":false,"contactInfo":[{"id":166463,"addressType":0,"city":null,"country":null,"deleted":false,"extension":null,"faxNumber":null,"organizationId":89086,"phoneNumber":null,"state":null,"street1":null,"street2":null,"zip":null}],"legacyKey":null,"parentLegacyKey":null,"legacyPrimaryContactKey":null,"showFacebookWall":false,"showTwitterFeed":false,"submissions":[],"visibility":"Public","isShownInPublicDirectory":true,"isAdminOnly":false,"categories":[]}